logsy/__init__.py
python_logsy-0.3.0.dist-info/licenses/LICENSE
python_logsy-0.3.0.dist-info/METADATA
python_logsy-0.3.0.dist-info/WHEEL
python_logsy-0.3.0.dist-info/top_level.txt
python_logsy-0.3.0.dist-info/RECORD
