Metadata-Version: 2.4
Name: python-logsy
Version: 0.3.0
Summary: A standardised logging configuration I use for a few things.
Author: Armandt van Zyl
Classifier: Environment :: Web Environment
Classifier: Intended Audience :: Developers
Classifier: Programming Language :: Python
Classifier: Programming Language :: Python :: 3
Classifier: Programming Language :: Python :: 3.8
Classifier: Programming Language :: Python :: 3 :: Only
Classifier: Topic :: Internet :: WWW/HTTP
Requires-Python: >=3.8
License-File: LICENSE
Provides-Extra: fluent
Requires-Dist: fluent-logger; extra == "fluent"
Requires-Dist: msgpack; extra == "fluent"
Requires-Dist: python-fluent-log-formatter; extra == "fluent"
Provides-Extra: sentry
Requires-Dist: sentry-sdk; extra == "sentry"
Dynamic: author
Dynamic: classifier
Dynamic: description
Dynamic: description-content-type
Dynamic: license-file
Dynamic: provides-extra
Dynamic: requires-python
Dynamic: summary
